flask_ms_oauth2/.version
flask_ms_oauth2/__init__.py
flask_ms_oauth2/config.py
flask_ms_oauth2/decorators.py
flask_ms_oauth2/ms_oauth2_manager.py
flask_ms_oauth2-1.0.0.dist-info/LICENSE
flask_ms_oauth2-1.0.0.dist-info/METADATA
flask_ms_oauth2-1.0.0.dist-info/WHEEL
flask_ms_oauth2-1.0.0.dist-info/top_level.txt
flask_ms_oauth2-1.0.0.dist-info/RECORD
